<annotation>
	<folder>train</folder>
	<filename>shutdown_1-f201c3c0-76e0-4d0b-8331-50275c7d5681.jpg</filename>
	<path>E:\Computer vision\Gotishell\Faster R-CNN\dataset\images\train\shutdown_1-f201c3c0-76e0-4d0b-8331-50275c7d5681.jpg</path>
	<source>
		<database>Unknown</database>
	</source>
	<size>
		<width>2688</width>
		<height>1520</height>
		<depth>3</depth>
	</size>
	<segmented>0</segmented>
	<object>
		<name>Helmets</name>
		<pose>Unspecified</pose>
		<truncated>0</truncated>
		<difficult>0</difficult>
		<bndbox>
			<xmin>532</xmin>
			<ymin>853</ymin>
			<xmax>630</xmax>
			<ymax>919</ymax>
		</bndbox>
	</object>
	<object>
		<name>Helmets</name>
		<pose>Unspecified</pose>
		<truncated>0</truncated>
		<difficult>0</difficult>
		<bndbox>
			<xmin>399</xmin>
			<ymin>772</ymin>
			<xmax>480</xmax>
			<ymax>841</ymax>
		</bndbox>
	</object>
	<object>
		<name>Helmets</name>
		<pose>Unspecified</pose>
		<truncated>0</truncated>
		<difficult>0</difficult>
		<bndbox>
			<xmin>483</xmin>
			<ymin>921</ymin>
			<xmax>585</xmax>
			<ymax>972</ymax>
		</bndbox>
	</object>
	<object>
		<name>Helmets</name>
		<pose>Unspecified</pose>
		<truncated>0</truncated>
		<difficult>0</difficult>
		<bndbox>
			<xmin>201</xmin>
			<ymin>878</ymin>
			<xmax>282</xmax>
			<ymax>927</ymax>
		</bndbox>
	</object>
	<object>
		<name>Boots</name>
		<pose>Unspecified</pose>
		<truncated>0</truncated>
		<difficult>0</difficult>
		<bndbox>
			<xmin>447</xmin>
			<ymin>1441</ymin>
			<xmax>558</xmax>
			<ymax>1481</ymax>
		</bndbox>
	</object>
	<object>
		<name>Boots</name>
		<pose>Unspecified</pose>
		<truncated>0</truncated>
		<difficult>0</difficult>
		<bndbox>
			<xmin>255</xmin>
			<ymin>1428</ymin>
			<xmax>375</xmax>
			<ymax>1492</ymax>
		</bndbox>
	</object>
	<object>
		<name>IFR_Suit</name>
		<pose>Unspecified</pose>
		<truncated>0</truncated>
		<difficult>0</difficult>
		<bndbox>
			<xmin>571</xmin>
			<ymin>924</ymin>
			<xmax>719</xmax>
			<ymax>1322</ymax>
		</bndbox>
	</object>
	<object>
		<name>IFR_Suit</name>
		<pose>Unspecified</pose>
		<truncated>0</truncated>
		<difficult>0</difficult>
		<bndbox>
			<xmin>440</xmin>
			<ymin>1000</ymin>
			<xmax>626</xmax>
			<ymax>1413</ymax>
		</bndbox>
	</object>
	<object>
		<name>IFR_Suit</name>
		<pose>Unspecified</pose>
		<truncated>0</truncated>
		<difficult>0</difficult>
		<bndbox>
			<xmin>194</xmin>
			<ymin>955</ymin>
			<xmax>364</xmax>
			<ymax>1275</ymax>
		</bndbox>
	</object>
</annotation>
